pyctdev/__init__.py
pyctdev/_conda.py
pyctdev/_pip.py
pyctdev/_version.py
pyctdev/condatemplate.yaml
pyctdev/util.py
pyctdev/_vendor/README.txt
pyctdev/_vendor/__init__.py
pyctdev/_vendor/tox-3.0.0.zip
pyctdev/_vendor/tox-pep-518.zip
pyctdev/_vendor/tox_wrapper.py
pyctdev/_vendor/virtualenv-15.2.0.zip
pyctdev-0.7.0.dist-info/LICENSE
pyctdev-0.7.0.dist-info/METADATA
pyctdev-0.7.0.dist-info/WHEEL
pyctdev-0.7.0.dist-info/top_level.txt
pyctdev-0.7.0.dist-info/RECORD
