Metadata-Version: 2.1
Name: pyctdev
Version: 0.7.0
Summary: python packaging common tasks for developers
Home-page: http://github.com/pyviz/pyctdev
License: BSD-3
Requires-Python: >=2.7
License-File: LICENSE
Requires-Dist: doit
Requires-Dist: cloudpickle
Requires-Dist: pluggy
Requires-Dist: py
Requires-Dist: pip (>=19.1.1)
Requires-Dist: tomli
Provides-Extra: ecosystem_conda
Requires-Dist: conda (>=4.4) ; extra == 'ecosystem_conda'
Requires-Dist: conda-build (>=3.10.1) ; extra == 'ecosystem_conda'
Provides-Extra: ecosystem_pip
Requires-Dist: tox ; extra == 'ecosystem_pip'
Requires-Dist: twine ; extra == 'ecosystem_pip'
Requires-Dist: wheel ; extra == 'ecosystem_pip'
Provides-Extra: tests
Requires-Dist: flake8 ; extra == 'tests'
